odoo/addons/shopinvader_product_manufactured_for/README.rst
odoo/addons/shopinvader_product_manufactured_for/__init__.py
odoo/addons/shopinvader_product_manufactured_for/__manifest__.py
odoo/addons/shopinvader_product_manufactured_for/data/ir_export_product.xml
odoo/addons/shopinvader_product_manufactured_for/i18n/shopinvader_product_manufactured_for.pot
odoo/addons/shopinvader_product_manufactured_for/models/__init__.py
odoo/addons/shopinvader_product_manufactured_for/models/shopinvader_variant.py
odoo/addons/shopinvader_product_manufactured_for/readme/CONTRIBUTORS.rst
odoo/addons/shopinvader_product_manufactured_for/readme/CREDITS.rst
odoo/addons/shopinvader_product_manufactured_for/readme/DESCRIPTION.rst
odoo/addons/shopinvader_product_manufactured_for/static/description/index.html
odoo/addons/shopinvader_product_manufactured_for/tests/__init__.py
odoo/addons/shopinvader_product_manufactured_for/tests/test_customer_special_product.py
odoo14_addon_shopinvader_product_manufactured_for-14.0.1.1.0.dist-info/METADATA
odoo14_addon_shopinvader_product_manufactured_for-14.0.1.1.0.dist-info/WHEEL
odoo14_addon_shopinvader_product_manufactured_for-14.0.1.1.0.dist-info/top_level.txt
odoo14_addon_shopinvader_product_manufactured_for-14.0.1.1.0.dist-info/RECORD
