Metadata-Version: 2.1
Name: odoo14-addon-shopinvader-product-manufactured-for
Version: 14.0.1.1.0
Summary: Manage Product Made Specially For Some Customers
Home-page: https://github.com/shopinvader/odoo-shopinvader
Author: Camptocamp
License: AGPL-3
Platform: UNKNOWN
Classifier: Programming Language :: Python
Classifier: Framework :: Odoo
Classifier: Framework :: Odoo :: 14.0
Classifier: License :: OSI Approved :: GNU Affero General Public License v3
Requires-Python: >=3.6
Requires-Dist: odoo14-addon-product-sale-manufactured-for
Requires-Dist: odoo14-addon-shopinvader
Requires-Dist: odoo <14.1dev,>=14.0a
